paquetes/__init__.py
paquetes/courses.py
paquetes/utils.py
paquetes-0.1.0.dist-info/METADATA
paquetes-0.1.0.dist-info/WHEEL
paquetes-0.1.0.dist-info/top_level.txt
paquetes-0.1.0.dist-info/RECORD
